photoshop_mcp_server/__init__.py
photoshop_mcp_server/app.py
photoshop_mcp_server/decorators.py
photoshop_mcp_server/ps_adapter/__init__.py
photoshop_mcp_server/ps_adapter/action_manager.py
photoshop_mcp_server/ps_adapter/application.py
photoshop_mcp_server/ps_adapter/utils.py
photoshop_mcp_server/registry.py
photoshop_mcp_server/resources/__init__.py
photoshop_mcp_server/resources/document_resources.py
photoshop_mcp_server/resources/registry.py
photoshop_mcp_server/server.py
photoshop_mcp_server/tools/__init__.py
photoshop_mcp_server/tools/document_tools.py
photoshop_mcp_server/tools/layer_tools.py
photoshop_mcp_server/tools/registry.py
photoshop_mcp_server/tools/session_tools.py
photoshop_mcp_server-0.1.10.dist-info/entry_points.txt
photoshop_mcp_server-0.1.10.dist-info/licenses/LICENSE
photoshop_mcp_server-0.1.10.dist-info/METADATA
photoshop_mcp_server-0.1.10.dist-info/WHEEL
photoshop_mcp_server-0.1.10.dist-info/RECORD
