Metadata-Version: 2.4
Name: photoshop-mcp-server
Version: 0.1.10
Summary: MCP Server for Photoshop integration using photoshop-python-api
License: MIT
License-File: LICENSE
Author: longhao
Author-email: hal.long@outlook.com
Requires-Python: >=3.10,<3.15
Classifier: License :: OSI Approved :: MIT License
Classifier: Operating System :: Microsoft :: Windows
Classifier: Programming Language :: Python :: 3
Classifier: Programming Language :: Python :: 3.10
Classifier: Programming Language :: Python :: 3.11
Classifier: Programming Language :: Python :: 3.12
Classifier: Programming Language :: Python :: 3.13
Classifier: Programming Language :: Python :: 3.14
Requires-Dist: loguru (>=0.7.3,<0.8.0)
Requires-Dist: mcp (>=1.6.0,<2.0.0)
Requires-Dist: photoshop-python-api (>=0.24.0,<0.25.0)
Requires-Dist: tenacity (>=9.0.0,<10.0.0)
Project-URL: Homepage, https://github.com/loonghao/photoshop-python-api-mcp-server
Project-URL: Issues, https://github.com/loonghao/photoshop-python-api-mcp-server/issues
Project-URL: Repository, https://github.com/loonghao/photoshop-python-api-mcp-server
